suplemon/__init__.py
suplemon/__main__.py
suplemon/cli.py
suplemon/config.py
suplemon/cursor.py
suplemon/editor.py
suplemon/file.py
suplemon/help.py
suplemon/helpers.py
suplemon/hex2xterm.py
suplemon/key_mappings.py
suplemon/lexer.py
suplemon/line.py
suplemon/logger.py
suplemon/main.py
suplemon/module_loader.py
suplemon/prompt.py
suplemon/suplemon_module.py
suplemon/themes.py
suplemon/ui.py
suplemon/viewer.py
suplemon/config/defaults.json
suplemon/config/keymap.json
suplemon/linelight/__init__.py
suplemon/linelight/color_map.py
suplemon/linelight/css.py
suplemon/linelight/diff.py
suplemon/linelight/html.py
suplemon/linelight/js.py
suplemon/linelight/json.py
suplemon/linelight/lua.py
suplemon/linelight/md.py
suplemon/linelight/php.py
suplemon/linelight/py.py
suplemon/modules/application_state.py
suplemon/modules/autocomplete.py
suplemon/modules/autodocstring.py
suplemon/modules/battery.py
suplemon/modules/bulk_delete.py
suplemon/modules/clock.py
suplemon/modules/comment.py
suplemon/modules/config.py
suplemon/modules/date.py
suplemon/modules/diff.py
suplemon/modules/eval.py
suplemon/modules/hostname.py
suplemon/modules/keymap.py
suplemon/modules/linter.py
suplemon/modules/lower.py
suplemon/modules/lstrip.py
suplemon/modules/paste.py
suplemon/modules/reload.py
suplemon/modules/replace_all.py
suplemon/modules/reverse.py
suplemon/modules/rstrip.py
suplemon/modules/save.py
suplemon/modules/save_all.py
suplemon/modules/sort_lines.py
suplemon/modules/strip.py
suplemon/modules/system_clipboard.py
suplemon/modules/tabstospaces.py
suplemon/modules/toggle_whitespace.py
suplemon/modules/upper.py
suplemon/themes/8colors.tmTheme
suplemon/themes/monokai.tmTheme
Wryten-1.42.10.dist-info/LICENSE
Wryten-1.42.10.dist-info/METADATA
Wryten-1.42.10.dist-info/WHEEL
Wryten-1.42.10.dist-info/entry_points.txt
Wryten-1.42.10.dist-info/top_level.txt
Wryten-1.42.10.dist-info/RECORD
