Metadata-Version: 2.1
Name: Wryten
Version: 1.42.10
Summary: Programable Console IDE
Home-page: https://github.com/streamcoders/wryten/
Author: Scott McCallum
Author-email: sm@intermine.com
License: UNKNOWN
Platform: UNKNOWN
Requires-Dist: pyperclip
Requires-Dist: pygments
Requires-Dist: wcwidth
Requires-Dist: windows-curses ; platform_system == "Windows"
